<annotation>
	<folder>img</folder>
	<filename>1_30d.jpg</filename>
	<path>1_30d.jpg</path>
	<source>
		<database>Unknown</database>
	</source>
	<size>
		<width>1707</width>
		<height>1280</height>
		<depth>3</depth>
	</size>
	<segmented>0</segmented>
	<object>
		<name>xmu</name>
		<pose>Unspecified</pose>
		<truncated>0</truncated>
		<difficult>0</difficult>
		<bndbox updated="yes">
			<xmin>779</xmin>
			<ymin>891</ymin>
			<xmax>930</xmax>
			<ymax>979</ymax>
		</bndbox>
	</object>
	<object>
		<name>man</name>
		<pose>Unspecified</pose>
		<truncated>0</truncated>
		<difficult>0</difficult>
		<bndbox updated="yes">
			<xmin>516</xmin>
			<ymin>1479</ymin>
			<xmax>742</xmax>
			<ymax>1869</ymax>
		</bndbox>
	</object>
	<object>
		<name>man</name>
		<pose>Unspecified</pose>
		<truncated>0</truncated>
		<difficult>0</difficult>
		<bndbox updated="yes">
			<xmin>1701</xmin>
			<ymin>777</ymin>
			<xmax>1876</xmax>
			<ymax>1081</ymax>
		</bndbox>
	</object>
	<object>
		<name>man</name>
		<pose>Unspecified</pose>
		<truncated>0</truncated>
		<difficult>0</difficult>
		<bndbox updated="yes">
			<xmin>1613</xmin>
			<ymin>790</ymin>
			<xmax>1788</xmax>
			<ymax>1092</ymax>
		</bndbox>
	</object>
	<object>
		<name>man</name>
		<pose>Unspecified</pose>
		<truncated>0</truncated>
		<difficult>0</difficult>
		<bndbox updated="yes">
			<xmin>1534</xmin>
			<ymin>810</ymin>
			<xmax>1639</xmax>
			<ymax>991</ymax>
		</bndbox>
	</object>
	<object>
		<name>man</name>
		<pose>Unspecified</pose>
		<truncated>0</truncated>
		<difficult>0</difficult>
		<bndbox updated="yes">
			<xmin>737</xmin>
			<ymin>1305</ymin>
			<xmax>790</xmax>
			<ymax>1396</ymax>
		</bndbox>
	</object>
	<object>
		<name>man</name>
		<pose>Unspecified</pose>
		<truncated>0</truncated>
		<difficult>0</difficult>
		<bndbox updated="yes">
			<xmin>1012</xmin>
			<ymin>1147</ymin>
			<xmax>1067</xmax>
			<ymax>1242</ymax>
		</bndbox>
	</object>
	<object>
		<name>man</name>
		<pose>Unspecified</pose>
		<truncated>0</truncated>
		<difficult>0</difficult>
		<bndbox updated="yes">
			<xmin>650</xmin>
			<ymin>1353</ymin>
			<xmax>703</xmax>
			<ymax>1444</ymax>
		</bndbox>
	</object>
	<object>
		<name>man</name>
		<pose>Unspecified</pose>
		<truncated>0</truncated>
		<difficult>0</difficult>
		<bndbox updated="yes">
			<xmin>575</xmin>
			<ymin>1373</ymin>
			<xmax>635</xmax>
			<ymax>1476</ymax>
		</bndbox>
	</object>
	<object>
		<name>man</name>
		<pose>Unspecified</pose>
		<truncated>0</truncated>
		<difficult>0</difficult>
		<bndbox updated="yes">
			<xmin>1432</xmin>
			<ymin>883</ymin>
			<xmax>1474</xmax>
			<ymax>945</ymax>
		</bndbox>
	</object>
</annotation>